chess_notation/__init__.py
chess_notation/__init__.pyi
chess_notation/notation.py
chess_notation/vocabulary.py
chess_notation/language/__init__.py
chess_notation/language/language.py
chess_notation/language/translations.json
chess_notation/represent/__init__.py
chess_notation/represent/represent.py
chess_notation/styles/__init__.py
chess_notation/styles/apply.py
chess_notation/styles/classify.py
chess_notation/styles/map.py
chess_notation/styles/styles.py
chess_notation-0.1.20.dist-info/METADATA
chess_notation-0.1.20.dist-info/WHEEL
chess_notation-0.1.20.dist-info/top_level.txt
chess_notation-0.1.20.dist-info/RECORD
