Metadata-Version: 2.1
Name: chess-notation
Version: 0.1.20
Summary: Tools for chess notation styles and languages
Author-email: Marcel Claramunt <marcel@moveread.com>
Project-URL: repo, https://github.com/moveread/chess-utils
Requires-Python: >=3.10
Requires-Dist: ramda
Requires-Dist: chess
Requires-Dist: pydantic
Requires-Dist: lazy-loader
